{
  "index": "概览",
  "part1-zhudong": "PART1：主动选择，才能接近梦想",
  "part2-weilai": "PART2：做从未来看正确的事",
  "part3-allin": "PART3：All in 一个波澜壮阔的事业",
  "part4-90hou": "PART4：90后新文明宣言",
  "part5-caifuziyou": "PART5：我在财富自由的路上等着你",
  "wechat-01-zhudongxuan": "延伸一：最刺人的一句话，不是成功，而是“主动”",
  "wechat-02-yazhuziwo": "延伸二：年轻时最该押注的，不是风口，是自己",
  "wechat-03-grown-up-is-choice": "延伸三：9 岁才是他真正成年的时候",
  "wechat-04-cognition-is-scarce": "延伸四：钱不稀缺，稀缺的是认知",
  "wechat-05-future-pricing": "延伸五：只为未来定价，不为过去买单",
  "wechat-06-invest-cases": "延伸六：他买特斯拉时，华尔街在做空它",
  "yuanwen": "📖 原文备查"
}
